Funk-0.5.0.dist-info/DESCRIPTION.rst
Funk-0.5.0.dist-info/METADATA
Funk-0.5.0.dist-info/RECORD
Funk-0.5.0.dist-info/WHEEL
Funk-0.5.0.dist-info/metadata.json
Funk-0.5.0.dist-info/top_level.txt
funk/__init__.py
funk/call.py
funk/error.py
funk/matchers.py
funk/pycompat.py
funk/sequence.py
funk/tools.py
funk/util.py
