Metadata-Version: 1.2
Name: Funk
Version: 0.5.0
Summary: A mocking framework for Python
Home-page: https://github.com/mwilliamson/funk
Author: Michael Williamson
Author-email: mike@zwobble.org
License: BSD License
Keywords: mock
Platform: UNKNOWN
Requires-Python: >=2.7, !=3.0.*, !=3.1.*, !=3.2.*, !=3.3.*
